main.py
mcp_weather_dfcyn-0.3.0.dist-info/METADATA
mcp_weather_dfcyn-0.3.0.dist-info/WHEEL
mcp_weather_dfcyn-0.3.0.dist-info/entry_points.txt
mcp_weather_dfcyn-0.3.0.dist-info/top_level.txt
mcp_weather_dfcyn-0.3.0.dist-info/RECORD
