Metadata-Version: 2.4
Name: mcp-weather-dfcyn
Version: 0.3.0
Summary: dfcyn天气查询的mcp
Requires-Python: >=3.10
Requires-Dist: httpx>=0.28.1
Requires-Dist: mcp>=1.14.1
Requires-Dist: requests>=2.32.5
